Metadata-Version: 1.0
Name: testpkgsam
Version: 0.2
Summary: The funniest joke in the world
Home-page: http://github.com/storborg/funniest
Author: Sam
Author-email: flyingcircus@example.com
License: MIT
Platform: UNKNOWN
